yikit/__init__.py
yikit/metrics.py
yikit/feature_selection/__init__.py
yikit/feature_selection/_test.py
yikit/feature_selection/filter_method.py
yikit/feature_selection/wrapper_method.py
yikit/models/__init__.py
yikit/models/_test.py
yikit/models/models.py
yikit/tools/__init__.py
yikit/tools/_test.py
yikit/tools/tools.py
yikit/tools/visualization.py
yikit-0.3.15.dist-info/LICENSE
yikit-0.3.15.dist-info/METADATA
yikit-0.3.15.dist-info/WHEEL
yikit-0.3.15.dist-info/top_level.txt
yikit-0.3.15.dist-info/RECORD
