Metadata-Version: 2.1
Name: yikit
Version: 0.3.15
Summary: This is my own tool kit.
Home-page: http://github.com/yu9824/yikit/
Author: yu9824
Author-email: yu.9824.job@gmail.com
Maintainer: yu9824
Maintainer-email: yu.9824.job@gmail.com
License: Apache License 2.0
Classifier: License :: OSI Approved :: Apache Software License
Classifier: Programming Language :: Python :: 3
Classifier: Programming Language :: Python :: 3.6
Classifier: Programming Language :: Python :: 3.7
Classifier: Programming Language :: Python :: 3.8
Classifier: Programming Language :: Python :: 3.9
License-File: LICENSE
Requires-Dist: scikit-learn (>=0.24.1)
Requires-Dist: numpy
Requires-Dist: pandas
Requires-Dist: tqdm
Requires-Dist: lightgbm
Requires-Dist: joblib
Requires-Dist: Boruta (==0.3)
Requires-Dist: scipy
Requires-Dist: optuna
Requires-Dist: matplotlib
Requires-Dist: seaborn
Requires-Dist: ngboost (==0.3.6)
